napari_script_editor/__init__.py
napari_script_editor/_chatgpt.py
napari_script_editor/_dock_widget.py
napari_script_editor/_scripts_directory.py
napari_script_editor/_tests/__init__.py
napari_script_editor/_tests/test_dock_widget.py
napari_script_editor-0.2.10.dist-info/LICENSE
napari_script_editor-0.2.10.dist-info/METADATA
napari_script_editor-0.2.10.dist-info/WHEEL
napari_script_editor-0.2.10.dist-info/entry_points.txt
napari_script_editor-0.2.10.dist-info/top_level.txt
napari_script_editor-0.2.10.dist-info/RECORD
