Metadata-Version: 2.1
Name: napari-script-editor
Version: 0.2.10
Summary: A python script editor for napari
Home-page: https://github.com/haesleinhuepf/napari-script-editor
Author: Robert Haase
Author-email: robert.haase@tu-dresden.de
License: BSD-3-Clause
Project-URL: Bug Tracker, https://github.com/haesleinhuepf/napari-script-editor/issues
Project-URL: Documentation, https://github.com/haesleinhuepf/napari-script-editor#README.md
Project-URL: Source Code, https://github.com/haesleinhuepf/napari-script-editor
Project-URL: User Support, https://github.com/haesleinhuepf/napari-script-editor/issues
Classifier: Development Status :: 3 - Alpha
Classifier: Intended Audience :: Developers
Classifier: Framework :: napari
Classifier: Topic :: Scientific/Engineering :: Image Processing
Classifier: Topic :: Text Editors :: Integrated Development Environments (IDE)
Classifier: Programming Language :: Python
Classifier: Programming Language :: Python :: 3
Classifier: Programming Language :: Python :: 3.7
Classifier: Programming Language :: Python :: 3.8
Classifier: Programming Language :: Python :: 3.9
Classifier: Operating System :: OS Independent
Classifier: License :: OSI Approved :: BSD License
Requires-Python: >=3.7
License-File: LICENSE
Requires-Dist: napari-plugin-engine (>=0.1.4)
Requires-Dist: numpy
Requires-Dist: napari
Requires-Dist: haesleinhuepf-pyqode.core (>=2.15.5)
Requires-Dist: haesleinhuepf-pyqode.python (>=2.15.2)
Requires-Dist: napari-tools-menu
Requires-Dist: jedi (>=0.18.0)
Requires-Dist: pyflakes (<=2.4.0)
Requires-Dist: imageio (!=2.22.1)
